thermometerb/__init__.py
thermometerb/thermometer.py
thermometerb/version.py
thermometerb-0.1.0.dist-info/LICENSE
thermometerb-0.1.0.dist-info/METADATA
thermometerb-0.1.0.dist-info/WHEEL
thermometerb-0.1.0.dist-info/top_level.txt
thermometerb-0.1.0.dist-info/RECORD
