Metadata-Version: 2.1
Name: thermometerb
Version: 0.1.0
Summary: Thermometer B is an example implementation of a class for accepting temperature data
Home-page: https://github.com/bacrossland/thermometerb
Author: Bryan Crossland
Author-email: bacrossland@gmail.com
Project-URL: Bug Tracker, https://github.com/bacrossland/thermometerb/issues
Platform: unix
Platform: linux
Platform: mac
Classifier: Development Status :: 5 - Production/Stable
Classifier: Environment :: Console
Classifier: Intended Audience :: Developers
Classifier: Intended Audience :: Education
Classifier: Intended Audience :: Information Technology
Classifier: License :: OSI Approved :: GNU General Public License v3 (GPLv3)
Classifier: Operating System :: MacOS :: MacOS X
Classifier: Operating System :: POSIX
Classifier: Operating System :: Microsoft :: Windows
Classifier: Programming Language :: Python
Classifier: Programming Language :: Python :: 3 :: Only
Classifier: Programming Language :: Python :: 3.10
Classifier: Topic :: Software Development :: Libraries
Requires-Python: >=3.10
License-File: LICENSE
